nonebot_plugin_omb/__init__.py
nonebot_plugin_omb/patch_alconna.py
nonebot_plugin_omb/patch_base.py
nonebot_plugin_omb/util.py
nonebot_plugin_omb-0.1.9.dist-info/LICENSE
nonebot_plugin_omb-0.1.9.dist-info/METADATA
nonebot_plugin_omb-0.1.9.dist-info/WHEEL
nonebot_plugin_omb-0.1.9.dist-info/RECORD
