Metadata-Version: 2.1
Name: nonebot-plugin-omb
Version: 0.1.9
Summary: ohh my bot!
License: MIT
Author: eya46
Author-email: 61458340+eya46@users.noreply.github.com
Requires-Python: >=3.9,<4.0
Classifier: License :: OSI Approved :: MIT License
Classifier: Programming Language :: Python :: 3
Classifier: Programming Language :: Python :: 3.9
Classifier: Programming Language :: Python :: 3.10
Classifier: Programming Language :: Python :: 3.11
Classifier: Programming Language :: Python :: 3.12
Classifier: Programming Language :: Python :: 3.13
Provides-Extra: alconna
Requires-Dist: nonebot-plugin-alconna (>=0.53.0) ; extra == "alconna"
Requires-Dist: nonebot2 (>=2.3.0,<3.0.0)
